bert/__init__.py
bert/args.py
bert/extract_feature.py
bert/graph.py
bert/modeling.py
bert/optimization.py
bert/tokenization.py
kashgari/__init__.py
kashgari/__version__.py
kashgari/callbacks.py
kashgari/corpus.py
kashgari/macros.py
kashgari/migeration.py
kashgari/migration.py
kashgari/utils.py
kashgari/version.py
kashgari/embeddings/__init__.py
kashgari/embeddings/bare_embedding.py
kashgari/embeddings/base_embedding.py
kashgari/embeddings/bert_embedding.py
kashgari/embeddings/bert_embedding_v2.py
kashgari/embeddings/gpt_2_embedding.py
kashgari/embeddings/numeric_feature_embedding.py
kashgari/embeddings/stacked_embedding.py
kashgari/embeddings/word_embedding.py
kashgari/layers/__init__.py
kashgari/layers/att_wgt_avg_layer.py
kashgari/layers/crf.py
kashgari/layers/kmax_pool_layer.py
kashgari/layers/non_masking_layer.py
kashgari/processors/__init__.py
kashgari/processors/base_processor.py
kashgari/processors/classification_processor.py
kashgari/processors/labeling_processor.py
kashgari/processors/scoring_processor.py
kashgari/tasks/__init__.py
kashgari/tasks/base_model.py
kashgari/tasks/classification/__init__.py
kashgari/tasks/classification/base_model.py
kashgari/tasks/classification/dpcnn_model.py
kashgari/tasks/classification/models.py
kashgari/tasks/labeling/__init__.py
kashgari/tasks/labeling/base_model.py
kashgari/tasks/labeling/experimental.py
kashgari/tasks/labeling/models.py
kashgari/tasks/scoring/__init__.py
kashgari/tasks/scoring/base_model.py
kashgari/tasks/scoring/models.py
kashgari/tokenizer/__init__.py
kashgari/tokenizer/base_tokenizer.py
kashgari/tokenizer/bert_tokenizer.py
kashgari/tokenizer/jieba_tokenizer.py
pysoftNLP/__init__.py
pysoftNLP/setup.py
pysoftNLP/test.py
pysoftNLP/bert/__init__.py
pysoftNLP/bert/args.py
pysoftNLP/bert/extract_feature.py
pysoftNLP/bert/graph.py
pysoftNLP/bert/modeling.py
pysoftNLP/bert/optimization.py
pysoftNLP/bert/tokenization.py
pysoftNLP/bert_pre training/__init__.py
pysoftNLP-0.0.4.dist-info/LICENSE
pysoftNLP-0.0.4.dist-info/METADATA
pysoftNLP-0.0.4.dist-info/WHEEL
pysoftNLP-0.0.4.dist-info/top_level.txt
pysoftNLP-0.0.4.dist-info/RECORD
