Metadata-Version: 2.1
Name: pysoftNLP
Version: 0.0.4
Summary: Python wrapper for pysoftNLP: Natural language processing project of 863 Software Incubator Co., Ltd
Home-page: https://github.com/pypa/sampleproject
Author: jiazhikai
Author-email: 15716539228@163.com
License: UNKNOWN
Platform: UNKNOWN
Classifier: Programming Language :: Python :: 3
Classifier: License :: OSI Approved :: MIT License
Classifier: Operating System :: OS Independent
Requires-Dist: tensorflow
